pible/__init__.py
pible/pible.py
pible/tests.py
pible/translations/__init__.py
pible/translations/esv/__init__.py
pible/translations/esv/esv.py
pible/translations/kjv/__init__.py
pible/translations/kjv/kjv.py
pible/translations/kjv/kjv_json/1Chronicles.json
pible/translations/kjv/kjv_json/1Corinthians.json
pible/translations/kjv/kjv_json/1John.json
pible/translations/kjv/kjv_json/1Kings.json
pible/translations/kjv/kjv_json/1Peter.json
pible/translations/kjv/kjv_json/1Samuel.json
pible/translations/kjv/kjv_json/1Thessalonians.json
pible/translations/kjv/kjv_json/1Timothy.json
pible/translations/kjv/kjv_json/2Chronicles.json
pible/translations/kjv/kjv_json/2Corinthians.json
pible/translations/kjv/kjv_json/2John.json
pible/translations/kjv/kjv_json/2Kings.json
pible/translations/kjv/kjv_json/2Peter.json
pible/translations/kjv/kjv_json/2Samuel.json
pible/translations/kjv/kjv_json/2Thessalonians.json
pible/translations/kjv/kjv_json/2Timothy.json
pible/translations/kjv/kjv_json/3John.json
pible/translations/kjv/kjv_json/Acts.json
pible/translations/kjv/kjv_json/Amos.json
pible/translations/kjv/kjv_json/Colossians.json
pible/translations/kjv/kjv_json/Daniel.json
pible/translations/kjv/kjv_json/Deuteronomy.json
pible/translations/kjv/kjv_json/Ecclesiastes.json
pible/translations/kjv/kjv_json/Ephesians.json
pible/translations/kjv/kjv_json/Esther.json
pible/translations/kjv/kjv_json/Exodus.json
pible/translations/kjv/kjv_json/Ezekiel.json
pible/translations/kjv/kjv_json/Ezra.json
pible/translations/kjv/kjv_json/Galatians.json
pible/translations/kjv/kjv_json/Genesis.json
pible/translations/kjv/kjv_json/Habakkuk.json
pible/translations/kjv/kjv_json/Haggai.json
pible/translations/kjv/kjv_json/Hebrews.json
pible/translations/kjv/kjv_json/Hosea.json
pible/translations/kjv/kjv_json/Isaiah.json
pible/translations/kjv/kjv_json/James.json
pible/translations/kjv/kjv_json/Jeremiah.json
pible/translations/kjv/kjv_json/Job.json
pible/translations/kjv/kjv_json/Joel.json
pible-0.4.1.dist-info/LICENSE
pible-0.4.1.dist-info/WHEEL
pible-0.4.1.dist-info/METADATA
pible-0.4.1.dist-info/RECORD
